{"ticker":"FND","updated":"2026-06-18T03:13:59Z","source":"yahoo","currency":"USD","income":[{"calendarYear":"2025","date":"2025-12-31","revenue":4684088000.0,"costOfRevenue":2640180000.0,"grossProfit":2043908000.0,"operatingExpenses":1773838000.0,"operatingIncome":270070000.0,"ebitda":519088000.0,"netIncome":208647000.0,"epsdiluted":1.92,"eps":1.92},{"calendarYear":"2024","date":"2024-12-31","revenue":4455770000.0,"costOfRevenue":2527519000.0,"grossProfit":1928251000.0,"operatingExpenses":1672075000.0,"operatingIncome":256176000.0,"ebitda":496190000.0,"netIncome":205872000.0,"epsdiluted":1.9,"eps":1.9},{"calendarYear":"2023","date":"2023-12-31","revenue":4413884000.0,"costOfRevenue":2555536000.0,"grossProfit":1858348000.0,"operatingExpenses":1536920000.0,"operatingIncome":321428000.0,"ebitda":529689000.0,"netIncome":245980000.0,"epsdiluted":2.28,"eps":2.28},{"calendarYear":"2022","date":"2022-12-31","revenue":4264473000.0,"costOfRevenue":2536757000.0,"grossProfit":1727716000.0,"operatingExpenses":1292314000.0,"operatingIncome":435402000.0,"ebitda":551783000.0,"netIncome":298195000.0,"epsdiluted":2.78,"eps":2.78},{"calendarYear":"2021","date":"2021-12-31","revenue":null,"costOfRevenue":null,"grossProfit":null,"operatingExpenses":null,"operatingIncome":null,"ebitda":null,"netIncome":null,"epsdiluted":null,"eps":null}],"balance":[{"calendarYear":"2025","date":"2025-12-31","cashAndCashEquivalents":249296000.0,"shortTermInvestments":null,"totalCurrentAssets":1527931000.0,"totalAssets":5469358000.0,"totalDebt":1991477000.0,"totalLiabilities":3060522000.0,"totalStockholdersEquity":2408836000.0,"netDebt":null},{"calendarYear":"2024","date":"2024-12-31","cashAndCashEquivalents":187669000.0,"shortTermInvestments":null,"totalCurrentAssets":1492385000.0,"totalAssets":5050478000.0,"totalDebt":1686558000.0,"totalLiabilities":2880320000.0,"totalStockholdersEquity":2170158000.0,"netDebt":8961000.0},{"calendarYear":"2023","date":"2023-12-31","cashAndCashEquivalents":34382000.0,"shortTermInvestments":null,"totalCurrentAssets":1316640000.0,"totalAssets":4662550000.0,"totalDebt":1625224000.0,"totalLiabilities":2731560000.0,"totalStockholdersEquity":1930990000.0,"netDebt":162660000.0},{"calendarYear":"2022","date":"2022-12-31","cashAndCashEquivalents":9794000.0,"shortTermInvestments":null,"totalCurrentAssets":1457485000.0,"totalAssets":4351242000.0,"totalDebt":1740854000.0,"totalLiabilities":2694066000.0,"totalStockholdersEquity":1657176000.0,"netDebt":397860000.0},{"calendarYear":"2021","date":"2021-12-31","cashAndCashEquivalents":null,"shortTermInvestments":null,"totalCurrentAssets":null,"totalAssets":null,"totalDebt":null,"totalLiabilities":null,"totalStockholdersEquity":null,"netDebt":58421000.0}],"cashflow":[{"calendarYear":"2025","date":"2025-12-31","operatingCashFlow":381836000.0,"capitalExpenditure":-317764000.0,"freeCashFlow":64072000.0,"stockBasedCompensation":29505000.0,"dividendsPaid":null},{"calendarYear":"2024","date":"2024-12-31","operatingCashFlow":603155000.0,"capitalExpenditure":-446826000.0,"freeCashFlow":156329000.0,"stockBasedCompensation":33695000.0,"dividendsPaid":null},{"calendarYear":"2023","date":"2023-12-31","operatingCashFlow":803589000.0,"capitalExpenditure":-547613000.0,"freeCashFlow":255976000.0,"stockBasedCompensation":27240000.0,"dividendsPaid":null},{"calendarYear":"2022","date":"2022-12-31","operatingCashFlow":112450000.0,"capitalExpenditure":-456600000.0,"freeCashFlow":-344150000.0,"stockBasedCompensation":22233000.0,"dividendsPaid":null},{"calendarYear":"2021","date":"2021-12-31","operatingCashFlow":null,"capitalExpenditure":null,"freeCashFlow":null,"stockBasedCompensation":null,"dividendsPaid":null}]}