{"ticker":"SPRY","updated":"2026-06-15T02:56:40Z","source":"yahoo","currency":"USD","income":[{"calendarYear":"2025","date":"2025-12-31","revenue":84278000.0,"costOfRevenue":20423000.0,"grossProfit":63855000.0,"operatingExpenses":243303000.0,"operatingIncome":-179448000.0,"ebitda":-168779000.0,"netIncome":-171298000.0,"epsdiluted":-1.74,"eps":-1.74},{"calendarYear":"2024","date":"2024-12-31","revenue":89149000.0,"costOfRevenue":977000.0,"grossProfit":88172000.0,"operatingExpenses":91255000.0,"operatingIncome":-3083000.0,"ebitda":8286000.0,"netIncome":7998000.0,"epsdiluted":0.08,"eps":0.08},{"calendarYear":"2023","date":"2023-12-31","revenue":30000.0,"costOfRevenue":0.0,"grossProfit":30000.0,"operatingExpenses":67550000.0,"operatingIncome":-67520000.0,"ebitda":-67520000.0,"netIncome":-54365000.0,"epsdiluted":-0.57,"eps":-0.57},{"calendarYear":"2022","date":"2022-12-31","revenue":1316000.0,"costOfRevenue":null,"grossProfit":null,"operatingExpenses":36832000.0,"operatingIncome":-35516000.0,"ebitda":-35197000.0,"netIncome":-34682000.0,"epsdiluted":-0.87,"eps":-0.87},{"calendarYear":"2021","date":"2021-12-31","revenue":null,"costOfRevenue":null,"grossProfit":null,"operatingExpenses":null,"operatingIncome":null,"ebitda":null,"netIncome":null,"epsdiluted":null,"eps":null}],"balance":[{"calendarYear":"2025","date":"2025-12-31","cashAndCashEquivalents":41317000.0,"shortTermInvestments":203669000.0,"totalCurrentAssets":284896000.0,"totalAssets":327652000.0,"totalDebt":96374000.0,"totalLiabilities":213394000.0,"totalStockholdersEquity":114258000.0,"netDebt":55057000.0},{"calendarYear":"2024","date":"2024-12-31","cashAndCashEquivalents":50817000.0,"shortTermInvestments":263205000.0,"totalCurrentAssets":334295000.0,"totalAssets":351153000.0,"totalDebt":42000.0,"totalLiabilities":94355000.0,"totalStockholdersEquity":256798000.0,"netDebt":null},{"calendarYear":"2023","date":"2023-12-31","cashAndCashEquivalents":70971000.0,"shortTermInvestments":157389000.0,"totalCurrentAssets":231726000.0,"totalAssets":233188000.0,"totalDebt":274000.0,"totalLiabilities":2428000.0,"totalStockholdersEquity":230760000.0,"netDebt":null},{"calendarYear":"2022","date":"2022-12-31","cashAndCashEquivalents":210518000.0,"shortTermInvestments":63863000.0,"totalCurrentAssets":277700000.0,"totalAssets":281435000.0,"totalDebt":481000.0,"totalLiabilities":8549000.0,"totalStockholdersEquity":272886000.0,"netDebt":null},{"calendarYear":"2021","date":"2021-12-31","cashAndCashEquivalents":null,"shortTermInvestments":null,"totalCurrentAssets":null,"totalAssets":null,"totalDebt":null,"totalLiabilities":null,"totalStockholdersEquity":null,"netDebt":null}],"cashflow":[{"calendarYear":"2025","date":"2025-12-31","operatingCashFlow":-170866000.0,"capitalExpenditure":-339000.0,"freeCashFlow":-171205000.0,"stockBasedCompensation":22095000.0,"dividendsPaid":null},{"calendarYear":"2024","date":"2024-12-31","operatingCashFlow":13548000.0,"capitalExpenditure":-563000.0,"freeCashFlow":12985000.0,"stockBasedCompensation":14534000.0,"dividendsPaid":null},{"calendarYear":"2023","date":"2023-12-31","operatingCashFlow":-59266000.0,"capitalExpenditure":-175000.0,"freeCashFlow":-59441000.0,"stockBasedCompensation":9235000.0,"dividendsPaid":null},{"calendarYear":"2022","date":"2022-12-31","operatingCashFlow":-40078000.0,"capitalExpenditure":-199000.0,"freeCashFlow":-40277000.0,"stockBasedCompensation":5843000.0,"dividendsPaid":null},{"calendarYear":"2021","date":"2021-12-31","operatingCashFlow":null,"capitalExpenditure":null,"freeCashFlow":null,"stockBasedCompensation":null,"dividendsPaid":null}]}