{"ticker":"ULCC","updated":"2026-06-18T03:15:12Z","source":"yahoo","currency":"USD","income":[{"calendarYear":"2025","date":"2025-12-31","revenue":3724000000.0,"costOfRevenue":3710000000.0,"grossProfit":14000000.0,"operatingExpenses":163000000.0,"operatingIncome":-149000000.0,"ebitda":-32000000.0,"netIncome":-137000000.0,"epsdiluted":-0.6,"eps":-0.6},{"calendarYear":"2024","date":"2024-12-31","revenue":3775000000.0,"costOfRevenue":3588000000.0,"grossProfit":187000000.0,"operatingExpenses":129000000.0,"operatingIncome":58000000.0,"ebitda":162000000.0,"netIncome":85000000.0,"epsdiluted":0.37,"eps":0.37},{"calendarYear":"2023","date":"2023-12-31","revenue":3589000000.0,"costOfRevenue":3287000000.0,"grossProfit":302000000.0,"operatingExpenses":305000000.0,"operatingIncome":-3000000.0,"ebitda":83000000.0,"netIncome":-11000000.0,"epsdiluted":-0.05,"eps":-0.05},{"calendarYear":"2022","date":"2022-12-31","revenue":3326000000.0,"costOfRevenue":3044000000.0,"grossProfit":282000000.0,"operatingExpenses":317000000.0,"operatingIncome":-35000000.0,"ebitda":10000000.0,"netIncome":-37000000.0,"epsdiluted":-0.17,"eps":-0.17},{"calendarYear":"2021","date":"2021-12-31","revenue":null,"costOfRevenue":null,"grossProfit":null,"operatingExpenses":null,"operatingIncome":null,"ebitda":null,"netIncome":null,"epsdiluted":null,"eps":null}],"balance":[{"calendarYear":"2025","date":"2025-12-31","cashAndCashEquivalents":671000000.0,"shortTermInvestments":null,"totalCurrentAssets":958000000.0,"totalAssets":7220000000.0,"totalDebt":5463000000.0,"totalLiabilities":6729000000.0,"totalStockholdersEquity":491000000.0,"netDebt":null},{"calendarYear":"2024","date":"2024-12-31","cashAndCashEquivalents":740000000.0,"shortTermInvestments":null,"totalCurrentAssets":990000000.0,"totalAssets":6153000000.0,"totalDebt":4468000000.0,"totalLiabilities":5549000000.0,"totalStockholdersEquity":604000000.0,"netDebt":null},{"calendarYear":"2023","date":"2023-12-31","cashAndCashEquivalents":609000000.0,"shortTermInvestments":null,"totalCurrentAssets":871000000.0,"totalAssets":4993000000.0,"totalDebt":3459000000.0,"totalLiabilities":4486000000.0,"totalStockholdersEquity":507000000.0,"netDebt":null},{"calendarYear":"2022","date":"2022-12-31","cashAndCashEquivalents":761000000.0,"shortTermInvestments":null,"totalCurrentAssets":1020000000.0,"totalAssets":4499000000.0,"totalDebt":2928000000.0,"totalLiabilities":3990000000.0,"totalStockholdersEquity":509000000.0,"netDebt":null},{"calendarYear":"2021","date":"2021-12-31","cashAndCashEquivalents":null,"shortTermInvestments":null,"totalCurrentAssets":null,"totalAssets":null,"totalDebt":null,"totalLiabilities":null,"totalStockholdersEquity":null,"netDebt":null}],"cashflow":[{"calendarYear":"2025","date":"2025-12-31","operatingCashFlow":-525000000.0,"capitalExpenditure":-99000000.0,"freeCashFlow":-624000000.0,"stockBasedCompensation":21000000.0,"dividendsPaid":null},{"calendarYear":"2024","date":"2024-12-31","operatingCashFlow":-82000000.0,"capitalExpenditure":-76000000.0,"freeCashFlow":-158000000.0,"stockBasedCompensation":16000000.0,"dividendsPaid":null},{"calendarYear":"2023","date":"2023-12-31","operatingCashFlow":-261000000.0,"capitalExpenditure":-87000000.0,"freeCashFlow":-348000000.0,"stockBasedCompensation":14000000.0,"dividendsPaid":null},{"calendarYear":"2022","date":"2022-12-31","operatingCashFlow":-78000000.0,"capitalExpenditure":-152000000.0,"freeCashFlow":-230000000.0,"stockBasedCompensation":15000000.0,"dividendsPaid":null},{"calendarYear":"2021","date":"2021-12-31","operatingCashFlow":null,"capitalExpenditure":null,"freeCashFlow":null,"stockBasedCompensation":null,"dividendsPaid":0.0}]}