{
  "qid": "Q1461050",
  "name": "Simon Johnson",
  "dateOfBirth": "1963-01-16",
  "birthPlace": "Sheffield",
  "image": "http://commons.wikimedia.org/wiki/Special:FilePath/Simon%20Johnson%2C%202024%20Nobel%20Prize%20Laureate%20in%20Economics%204%20%28cropped%29.jpg",
  "occupations": [
    "university teacher",
    "economist"
  ],
  "education": [
    "Massachusetts Institute of Technology",
    "University of Manchester",
    "University of Oxford"
  ],
  "employers": [
    {
      "company": "MIT Sloan School of Management",
      "start": null,
      "end": null
    },
    {
      "company": "Duke University",
      "start": null,
      "end": null
    },
    {
      "company": "Massachusetts Institute of Technology",
      "start": null,
      "end": null
    }
  ],
  "positions": [
    {
      "title": "chief economist",
      "company": null,
      "start": "2007-03-01",
      "end": "2008-08-01"
    }
  ],
  "currentTickers": [
    "FNMA"
  ]
}