{
  "date": "2026-06-14",
  "regime": "neutral",
  "confidence": 0.879,
  "scores": {
    "macro": 0.235,
    "liquidity": -0.161,
    "volatility": 0.264,
    "valuation": -1.0,
    "trend": 0.904,
    "breadth": 0.273,
    "commodity": 0.088,
    "crypto": -0.672
  },
  "signal_confidences": {
    "macro": 1.0,
    "liquidity": 0.333,
    "volatility": 1.0,
    "valuation": 0.7,
    "trend": 1.0,
    "breadth": 1.0,
    "commodity": 1.0,
    "crypto": 1.0
  },
  "current_probabilities": {
    "expansion": 0.3152,
    "risk_on_melt_up": 0.1097,
    "inflation_shock": 0.031,
    "recession_fear": 0.0034,
    "risk_off": 0.0386,
    "neutral": 0.5021
  },
  "drivers": [
    {
      "signal": "trend",
      "score": 0.904,
      "confidence": 1.0,
      "weight": 0.904,
      "direction": "bullish"
    },
    {
      "signal": "valuation",
      "score": -1.0,
      "confidence": 0.7,
      "weight": 0.7,
      "direction": "bearish"
    },
    {
      "signal": "crypto",
      "score": -0.672,
      "confidence": 1.0,
      "weight": 0.672,
      "direction": "bearish"
    }
  ],
  "signal_notes": {
    "macro": {
      "avg_1m_sector_return": 0.0118,
      "n_sectors": 11
    },
    "liquidity": {
      "hyg_minus_lqd_1m": -0.0032
    },
    "volatility": {
      "vix_level": 17.68,
      "vix9d_over_vix": 0.9762
    },
    "valuation": {
      "spy_pe": 26.57
    },
    "trend": {
      "spy_price": 741.75,
      "sma50": 722.8,
      "sma200": 686.3,
      "pct_above_200dma": 0.0808
    },
    "breadth": {
      "pct_sectors_above_50dma": 0.636,
      "n_above": 7,
      "n_total": 11
    },
    "commodity": {
      "copper_60d_return": 0.0785,
      "oil_60d_return": -0.1433,
      "gold_oil_ratio": 49.939,
      "gold_oil_zscore": -0.845,
      "n_components": 3
    },
    "crypto": {
      "btc_30d_return": -0.1864,
      "btc_pct_from_50dma": -0.1326,
      "eth_30d_return": -0.2461,
      "n_components": 3
    }
  },
  "computed_at": "2026-06-14T05:22:02+00:00",
  "transitions": {
    "1_step": {
      "expansion": 0.1429,
      "risk_on_melt_up": 0.1429,
      "inflation_shock": 0.1429,
      "recession_fear": 0.1429,
      "risk_off": 0.1429,
      "neutral": 0.2857
    },
    "5_step": {
      "expansion": 0.1622,
      "risk_on_melt_up": 0.1622,
      "inflation_shock": 0.1622,
      "recession_fear": 0.1622,
      "risk_off": 0.1622,
      "neutral": 0.1892
    },
    "20_step": {
      "expansion": 0.1622,
      "risk_on_melt_up": 0.1622,
      "inflation_shock": 0.1622,
      "recession_fear": 0.1622,
      "risk_off": 0.1622,
      "neutral": 0.1892
    }
  },
  "stationary": {
    "expansion": 0.1622,
    "risk_on_melt_up": 0.1622,
    "inflation_shock": 0.1622,
    "recession_fear": 0.1622,
    "risk_off": 0.1622,
    "neutral": 0.1892
  },
  "expected_persistence_days": 1.4,
  "transition_matrix": [
    [
      0.1667,
      0.1667,
      0.1667,
      0.1667,
      0.1667,
      0.1667
    ],
    [
      0.1667,
      0.1667,
      0.1667,
      0.1667,
      0.1667,
      0.1667
    ],
    [
      0.1667,
      0.1667,
      0.1667,
      0.1667,
      0.1667,
      0.1667
    ],
    [
      0.1667,
      0.1667,
      0.1667,
      0.1667,
      0.1667,
      0.1667
    ],
    [
      0.1667,
      0.1667,
      0.1667,
      0.1667,
      0.1667,
      0.1667
    ],
    [
      0.1429,
      0.1429,
      0.1429,
      0.1429,
      0.1429,
      0.2857
    ]
  ],
  "transition_observation_count": 1,
  "transition_warning": "Only 1 transitions observed \u2014 need \u226560 for high confidence",
  "transitions_computed_at": "2026-06-14T05:22:02+00:00"
}